queens_solver/__init__.py
queens_solver/board.py
queens_solver/main.py
queens_solver/solver.py
queens_solver-0.3.2.dist-info/WHEEL
queens_solver-0.3.2.dist-info/entry_points.txt
queens_solver-0.3.2.dist-info/METADATA
queens_solver-0.3.2.dist-info/RECORD
