Metadata-Version: 2.3
Name: queens-solver
Version: 0.3.2
Summary: coming soon
Author: Benjamin Groves
Author-email: Benjamin Groves <benjaminjgroves@gmail.com>
Requires-Dist: colored>=2.3.1
Requires-Dist: seaborn>=0.13.2
Requires-Python: >=3.14
